{"message":"Request Successful","data":[{"id":"u4OLtt","name":"Main Brewery","streetAddress":"3178-B Bladensburg Rd. NE","locality":"Washington","region":"District of Columbia","postalCode":"20018","phone":"202-621-8890","website":"http:\/\/www.dcbrau.com\/","hoursOfOperation":"*Hours are typically 1-4pm, Saturdays. Follow us on Facebook & Twitter for schedule changes.\r\nTours will be held at 1:30, 2:30, & 3:30.","latitude":38.929628,"longitude":-76.960438,"isPrimary":"Y","inPlanning":"N","isClosed":"N","openToPublic":"Y","locationType":"micro","locationTypeDisplay":"Micro Brewery","countryIsoCode":"US","yearOpened":"2009","status":"verified","statusDisplay":"Verified","createDate":"2012-01-03 02:41:52","updateDate":"2014-07-23 19:11:34","country":{"isoCode":"US","name":"UNITED STATES","displayName":"United States","isoThree":"USA","numberCode":840,"createDate":"2012-01-03 02:41:33"}}],"status":"success"}